{
    "actors":{
        "ModbusExampleActor":{
            "formals":[],
            "instances":{
                "commInitiator":{
                    "actuals":[],
                    "type":"ComputationalComponent"
                },
                "modbus":{
                    "actuals":[
                        {
                            "name":"slaveaddress",
                            "value":10
                        },
                        {
                            "name":"port",
                            "value":"UART2"
                        },
                        {
                            "name":"baudrate",
                            "value":115200
                        },
                        {
                            "name":"serialTimeout",
                            "value":1
                        }
                    ],
                    "type":"ModbusUartReqRepDevice"
                }
            },
            "internals":[],
            "locals":[
                {
                    "type":"ModbusStatusRequest"
                },
                {
                    "type":"ModbusStatus"
                },
                {
                    "type":"ModbusCommand"
                },
                {
                    "type":"ModbusResponse"
                }
            ],
            "usage":{
                "cpu":{},
                "mem":{},
                "net":{},
                "spc":{}
            }
        },
        "ModbusLogger":{
            "formals":[],
            "instances":{
                "logger":{
                    "actuals":[
                        {
                            "name":"db_host",
                            "value":"127.0.0.1"
                        },
                        {
                            "name":"db_port",
                            "value":8086
                        },
                        {
                            "name":"db_name",
                            "value":"ModbusIO"
                        },
                        {
                            "name":"db_user",
                            "value":"riaps"
                        },
                        {
                            "name":"db_password",
                            "value":"riaps"
                        }
                    ],
                    "type":"Logger"
                }
            },
            "internals":[],
            "locals":[],
            "usage":{
                "cpu":{},
                "mem":{},
                "net":{},
                "spc":{}
            }
        }
    },
    "components":{
        "ComputationalComponent":{
            "formals":[],
            "language":"default",
            "name":"ComputationalComponent",
            "ports":{
                "anss":{},
                "clts":{},
                "inss":{},
                "pubs":{
                    "tx_modbusData":{
                        "timed":false,
                        "type":"ModbusData"
                    }
                },
                "qrys":{},
                "reps":{},
                "reqs":{
                    "modbusCommandReqPort":{
                        "deadline":0,
                        "rep_type":"ModbusResponse",
                        "req_type":"ModbusCommand",
                        "timed":false
                    },
                    "modbusStatusReqPort":{
                        "deadline":0,
                        "rep_type":"ModbusStatus",
                        "req_type":"ModbusStatusRequest",
                        "timed":false
                    }
                },
                "srvs":{},
                "subs":{},
                "tims":{
                    "clock":{
                        "deadline":0,
                        "period":5000
                    }
                }
            }
        },
        "Logger":{
            "formals":[
                {
                    "default":"127.0.0.1",
                    "name":"db_host"
                },
                {
                    "default":8086,
                    "name":"db_port"
                },
                {
                    "default":"MOdbusIO",
                    "name":"db_name"
                },
                {
                    "default":"riaps",
                    "name":"db_user"
                },
                {
                    "default":"riaps",
                    "name":"db_password"
                }
            ],
            "language":"default",
            "name":"Logger",
            "ports":{
                "anss":{},
                "clts":{},
                "inss":{},
                "pubs":{},
                "qrys":{},
                "reps":{},
                "reqs":{},
                "srvs":{},
                "subs":{
                    "rx_modbusData":{
                        "deadline":0,
                        "timed":false,
                        "type":"ModbusData"
                    }
                },
                "tims":{}
            }
        }
    },
    "devices":{
        "ModbusUartReqRepDevice":{
            "formals":[
                {
                    "default":10,
                    "name":"slaveaddress"
                },
                {
                    "default":"UART2",
                    "name":"port"
                },
                {
                    "default":115200,
                    "name":"baudrate"
                },
                {
                    "default":1.0,
                    "name":"serialTimeout"
                }
            ],
            "language":"default",
            "name":"ModbusUartReqRepDevice",
            "ports":{
                "anss":{},
                "clts":{},
                "inss":{},
                "pubs":{},
                "qrys":{},
                "reps":{
                    "modbusCommandRepPort":{
                        "deadline":0,
                        "rep_type":"ModbusResponse",
                        "req_type":"ModbusCommand",
                        "timed":false
                    },
                    "modbusStatusRepPort":{
                        "deadline":0,
                        "rep_type":"ModbusStatus",
                        "req_type":"ModbusStatusRequest",
                        "timed":false
                    }
                },
                "reqs":{},
                "srvs":{},
                "subs":{},
                "tims":{}
            }
        }
    },
    "groups":[],
    "libraries":[
        {
            "name":"serialModbusLib"
        }
    ],
    "messages":[
        {
            "name":"ModbusStatusRequest"
        },
        {
            "name":"ModbusStatus"
        },
        {
            "name":"ModbusCommand"
        },
        {
            "name":"ModbusResponse"
        },
        {
            "name":"ModbusData"
        }
    ],
    "name":"RIAPSModbusReqRepUART"
}