{
    "actors":{
        "Collector":{
            "formals":[
                {
                    "name":"TsArg"
                },
                {
                    "name":"ipArg"
                }
            ],
            "instances":{
                "gateway":{
                    "actuals":[
                        {
                            "name":"Ts",
                            "param":"TsArg"
                        },
                        {
                            "name":"ip",
                            "param":"ipArg"
                        }
                    ],
                    "type":"Gateway"
                },
                "modbusinstance":{
                    "actuals":[
                        {
                            "name":"slaveaddress",
                            "value":10
                        },
                        {
                            "name":"port",
                            "value":"UART1"
                        },
                        {
                            "name":"baudrate",
                            "value":115200
                        },
                        {
                            "name":"numholdreg",
                            "value":3
                        },
                        {
                            "name":"numinputreg",
                            "value":5
                        },
                        {
                            "name":"addr",
                            "value":1
                        },
                        {
                            "name":"nb",
                            "value":4
                        }
                    ],
                    "type":"ModbusUART"
                }
            },
            "internals":[],
            "locals":[
                {
                    "type":"Voltage"
                }
            ],
            "usage":{
                "cpu":{},
                "mem":{},
                "net":{},
                "spc":{}
            }
        },
        "OpalIOActor":{
            "formals":[],
            "instances":{
                "c37receiver":{
                    "actuals":[
                        {
                            "name":"pmu_ip",
                            "value":"192.168.10.101"
                        },
                        {
                            "name":"pmu_port",
                            "value":7200
                        }
                    ],
                    "type":"C37Receiver1P13A2D"
                },
                "processor":{
                    "actuals":[],
                    "type":"Processor"
                }
            },
            "internals":[],
            "locals":[
                {
                    "type":"C37Data"
                },
                {
                    "type":"C37Header"
                },
                {
                    "type":"C37Config"
                }
            ],
            "usage":{
                "cpu":{},
                "mem":{},
                "net":{},
                "spc":{}
            }
        }
    },
    "components":{
        "Gateway":{
            "formals":[
                {
                    "default":0.1,
                    "name":"Ts"
                },
                {
                    "default":111,
                    "name":"ip"
                }
            ],
            "language":"default",
            "name":"Gateway",
            "ports":{
                "anss":{},
                "clts":{},
                "inss":{},
                "pubs":{
                    "thisReady":{
                        "timed":false,
                        "type":"NodeData"
                    }
                },
                "qrys":{},
                "reps":{},
                "reqs":{},
                "srvs":{},
                "subs":{
                    "currentvoltage":{
                        "deadline":0,
                        "timed":false,
                        "type":"Voltage"
                    },
                    "nodeReady":{
                        "deadline":0,
                        "timed":false,
                        "type":"NodeData"
                    },
                    "rx_phasorData":{
                        "deadline":0,
                        "timed":false,
                        "type":"PhasorData"
                    }
                },
                "tims":{}
            }
        },
        "Processor":{
            "formals":[],
            "language":"default",
            "name":"Processor",
            "ports":{
                "anss":{},
                "clts":{},
                "inss":{},
                "pubs":{
                    "tx_phasorData":{
                        "timed":false,
                        "type":"PhasorData"
                    }
                },
                "qrys":{},
                "reps":{},
                "reqs":{},
                "srvs":{},
                "subs":{
                    "rx_c37config":{
                        "deadline":0,
                        "timed":false,
                        "type":"C37Config"
                    },
                    "rx_c37data":{
                        "deadline":0,
                        "timed":false,
                        "type":"C37Data"
                    },
                    "rx_c37header":{
                        "deadline":0,
                        "timed":false,
                        "type":"C37Header"
                    }
                },
                "tims":{}
            }
        }
    },
    "devices":{
        "C37Receiver1P13A2D":{
            "formals":[
                {
                    "default":"192.168.10.101",
                    "name":"pmu_ip"
                },
                {
                    "default":7200,
                    "name":"pmu_port"
                }
            ],
            "language":"default",
            "name":"C37Receiver1P13A2D",
            "ports":{
                "anss":{},
                "clts":{},
                "inss":{
                    "config_queue":{
                        "spec":false
                    },
                    "data_queue":{
                        "spec":false
                    },
                    "header_queue":{
                        "spec":false
                    }
                },
                "pubs":{
                    "c37config":{
                        "timed":false,
                        "type":"C37Config"
                    },
                    "c37data":{
                        "timed":false,
                        "type":"C37Data"
                    },
                    "c37header":{
                        "timed":false,
                        "type":"C37Header"
                    }
                },
                "qrys":{},
                "reps":{},
                "reqs":{},
                "srvs":{},
                "subs":{},
                "tims":{
                    "clock":{
                        "deadline":0,
                        "period":2000
                    }
                }
            }
        },
        "ModbusUART":{
            "formals":[
                {
                    "default":10,
                    "name":"slaveaddress"
                },
                {
                    "default":"UART1",
                    "name":"port"
                },
                {
                    "default":115200,
                    "name":"baudrate"
                },
                {
                    "default":3,
                    "name":"numholdreg"
                },
                {
                    "default":4,
                    "name":"numinputreg"
                },
                {
                    "default":0,
                    "name":"addr"
                },
                {
                    "default":4,
                    "name":"nb"
                }
            ],
            "language":"cpp",
            "name":"ModbusUART",
            "ports":{
                "anss":{},
                "clts":{},
                "inss":{},
                "pubs":{
                    "currentvoltage":{
                        "timed":false,
                        "type":"Voltage"
                    }
                },
                "qrys":{},
                "reps":{},
                "reqs":{},
                "srvs":{},
                "subs":{},
                "tims":{
                    "clock":{
                        "deadline":0,
                        "period":50
                    }
                }
            }
        }
    },
    "groups":[],
    "libraries":[
        {
            "name":"pypmu"
        }
    ],
    "messages":[
        {
            "name":"Voltage"
        },
        {
            "name":"NodeData"
        },
        {
            "name":"C37Data"
        },
        {
            "name":"C37Header"
        },
        {
            "name":"C37Config"
        },
        {
            "name":"PhasorData"
        }
    ],
    "name":"DistributedVoltage"
}